sydar/Util.py
sydar/Automata.py
sydar/cvx_gen.py
sydar/symbol_table.py
sydar/command_line.py
sydar/parser.py
sydar/PartitionRefinement.py
sydar/__init__.py
sydar/utils.py
sydar/helpers.py
sydar/Sequence.py
sydar/Graph.py
sydar/region.py
sydar-0.14.3.dist-info/RECORD
sydar-0.14.3.dist-info/METADATA
sydar-0.14.3.dist-info/metadata.json
sydar-0.14.3.dist-info/entry_points.txt
sydar-0.14.3.dist-info/DESCRIPTION.rst
sydar-0.14.3.dist-info/WHEEL
sydar-0.14.3.dist-info/top_level.txt
