Metadata-Version: 2.0
Name: sydar
Version: 0.14.3
Summary: Synthesis Done Approximately Right
Home-page: https://github.com/u-t-autonomous/sydar.git
Author: Mohammed Alshiekh
Author-email: sahabi@gmail.com
License: BSD
Platform: UNKNOWN
Requires-Dist: scipy
Requires-Dist: pyparsing
Requires-Dist: numpy
